bluestackspatcher_nougat/LICENSE
bluestackspatcher_nougat/README.MD
bluestackspatcher_nougat/__init__.py
bluestackspatcher_nougat/requirements.txt
bluestackspatcher_nougat/thirdparty.json
bluestackspatcher_nougat-0.12.dist-info/LICENSE.rst
bluestackspatcher_nougat-0.12.dist-info/METADATA
bluestackspatcher_nougat-0.12.dist-info/WHEEL
bluestackspatcher_nougat-0.12.dist-info/top_level.txt
bluestackspatcher_nougat-0.12.dist-info/RECORD
