Metadata-Version: 2.1
Name: bluestackspatcher-nougat
Version: 0.12
Summary: Updates IMEI/IMSI on BlueStacks 5.11.1002 / N32 / 32 bit / Android Nougat (probably other versions as well)
Home-page: https://github.com/hansalemaos/bluestackspatcher_nougat
Author: Johannes Fischer
Author-email: <aulasparticularesdealemaosp@gmail.com>
License: MIT
Keywords: bluestacks,android,adb
Classifier: Development Status :: 4 - Beta
Classifier: Programming Language :: Python :: 3 :: Only
Classifier: Programming Language :: Python :: 3.9
Classifier: Topic :: Scientific/Engineering :: Visualization
Classifier: Topic :: Software Development :: Libraries :: Python Modules
Classifier: Topic :: Text Editors :: Text Processing
Classifier: Topic :: Text Processing :: General
Classifier: Topic :: Text Processing :: Indexing
Classifier: Topic :: Text Processing :: Filters
Classifier: Topic :: Utilities
License-File: LICENSE.rst
Requires-Dist: a-pandas-ex-bstcfg2df
Requires-Dist: bstconnect
Requires-Dist: FastCopyFast
Requires-Dist: flatten-everything
Requires-Dist: getdefgateway
Requires-Dist: getpathfromreg
Requires-Dist: kthread-sleep
Requires-Dist: pandas
Requires-Dist: pdwinauto
Requires-Dist: PrettyColorPrinter
Requires-Dist: procobserver
Requires-Dist: psutil
Requires-Dist: regex
Requires-Dist: subprocess-print-and-capture
